pybind11_fmm/__init__.py
pybind11_fmm/__main__.py
pybind11_fmm/_core/__init__.pyi
pybind11_fmm/_core/fmm.pyi
pybind11_fmm/_core.cp310-win_amd64.pyd
pybind11_fmm-0.0.2.dist-info/METADATA
pybind11_fmm-0.0.2.dist-info/WHEEL
pybind11_fmm-0.0.2.dist-info/licenses/LICENSE
pybind11_fmm-0.0.2.dist-info/RECORD
